{
 "copyright": "(C) APNIC Pty/Ltd. Re-use with attribution permitted",
  "description": "Estimates of user population per AS",
  "Date": "28/03/2026",
  "Window": "120 Days",
 "Data": [
{"rank":1,"AS":27947,"Description":"Telconet S.A","CC":"EC","Users":3323550,"Percent of CC Pop":29.24,"Percent of Internet":0.0796,"Samples":4697079},
{"rank":2,"AS":52468,"Description":"UFINET PANAMA S.A.","CC":"EC","Users":1592874,"Percent of CC Pop":14.01,"Percent of Internet":0.0382,"Samples":2252112},
{"rank":3,"AS":27738,"Description":"Ecuadortelecom S.A.","CC":"EC","Users":1001198,"Percent of CC Pop":8.81,"Percent of Internet":0.0240,"Samples":1415922},
{"rank":4,"AS":14522,"Description":"SERVICIOS DE TELECOMUNICACIONES SETEL S.A. XTRIM EC","CC":"EC","Users":755927,"Percent of CC Pop":6.65,"Percent of Internet":0.0181,"Samples":1066144},
{"rank":5,"AS":23487,"Description":"CONECEL","CC":"EC","Users":727393,"Percent of CC Pop":6.40,"Percent of Internet":0.0174,"Samples":1027236},
{"rank":6,"AS":22724,"Description":"PUNTONET S.A.","CC":"EC","Users":644894,"Percent of CC Pop":5.67,"Percent of Internet":0.0155,"Samples":911112},
{"rank":7,"AS":263238,"Description":"Eliana Vanessa Morocho Ona","CC":"EC","Users":550902,"Percent of CC Pop":4.85,"Percent of Internet":0.0132,"Samples":777715},
{"rank":8,"AS":7315,"Description":"Otecel S.A.","CC":"EC","Users":326823,"Percent of CC Pop":2.88,"Percent of Internet":0.0078,"Samples":462528},
{"rank":9,"AS":28006,"Description":"CORPORACION NACIONAL DE TELECOMUNICACIONES - CNT EP","CC":"EC","Users":273611,"Percent of CC Pop":2.41,"Percent of Internet":0.0066,"Samples":368349},
{"rank":10,"AS":264825,"Description":"TELEALFACOM S.A.S.","CC":"EC","Users":189068,"Percent of CC Pop":1.66,"Percent of Internet":0.0045,"Samples":267764},
{"rank":11,"AS":27668,"Description":"ETAPA EP","CC":"EC","Users":149516,"Percent of CC Pop":1.32,"Percent of Internet":0.0036,"Samples":211615},
{"rank":12,"AS":271929,"Description":"INTERCOMMERCE S.A.","CC":"EC","Users":116388,"Percent of CC Pop":1.02,"Percent of Internet":0.0028,"Samples":164557},
{"rank":13,"AS":269853,"Description":"CBVISION S.A.","CC":"EC","Users":114369,"Percent of CC Pop":1.01,"Percent of Internet":0.0027,"Samples":161368},
{"rank":14,"AS":267684,"Description":"VISIONMAGICA SOCIEDAD ANONIMA","CC":"EC","Users":99510,"Percent of CC Pop":0.88,"Percent of Internet":0.0024,"Samples":140715},
{"rank":15,"AS":19114,"Description":"Otecel S.A.","CC":"EC","Users":99246,"Percent of CC Pop":0.87,"Percent of Internet":0.0024,"Samples":140462},
{"rank":16,"AS":271874,"Description":"SERVITRACTOR S.A.","CC":"EC","Users":89590,"Percent of CC Pop":0.79,"Percent of Internet":0.0021,"Samples":126576},
{"rank":17,"AS":263792,"Description":"IN.PLANET S. A","CC":"EC","Users":82250,"Percent of CC Pop":0.72,"Percent of Internet":0.0020,"Samples":116657},
{"rank":18,"AS":271795,"Description":"SERVITELCONET CIA. LTDA.","CC":"EC","Users":81184,"Percent of CC Pop":0.71,"Percent of Internet":0.0019,"Samples":114593},
{"rank":19,"AS":270049,"Description":"MARVICNET CIA LTDA","CC":"EC","Users":58190,"Percent of CC Pop":0.51,"Percent of Internet":0.0014,"Samples":82139},
{"rank":20,"AS":14593,"Description":"SPACEX-STARLINK - Space Exploration Technologies Corporation","CC":"EC","Users":55361,"Percent of CC Pop":0.49,"Percent of Internet":0.0013,"Samples":78164},
{"rank":21,"AS":262223,"Description":"NECUSOFT CIA. LTDA. NETTPLUS","CC":"EC","Users":48207,"Percent of CC Pop":0.42,"Percent of Internet":0.0012,"Samples":68424},
{"rank":22,"AS":265799,"Description":"EXPERTSERVI S.A.","CC":"EC","Users":48154,"Percent of CC Pop":0.42,"Percent of Internet":0.0012,"Samples":67568},
{"rank":23,"AS":269831,"Description":"SERVICIO DE TELECOMUNICACIONES OROBLA S. A","CC":"EC","Users":47940,"Percent of CC Pop":0.42,"Percent of Internet":0.0011,"Samples":67638},
{"rank":24,"AS":52238,"Description":"SPEEDYCOM","CC":"EC","Users":47775,"Percent of CC Pop":0.42,"Percent of Internet":0.0011,"Samples":68029},
{"rank":25,"AS":266904,"Description":"ALCIVAR ESPIN DANNY ALEXANDER OptiCom","CC":"EC","Users":41914,"Percent of CC Pop":0.37,"Percent of Internet":0.0010,"Samples":59074},
{"rank":26,"AS":267756,"Description":"TRANSCORPORACION S.A.","CC":"EC","Users":39804,"Percent of CC Pop":0.35,"Percent of Internet":0.0010,"Samples":56059},
{"rank":27,"AS":269838,"Description":"MENA CORNEJO HECTOR ELIAS TECMESH","CC":"EC","Users":32635,"Percent of CC Pop":0.29,"Percent of Internet":0.0008,"Samples":46363},
{"rank":28,"AS":273034,"Description":"COMPANIA DE TELECOMUNICACIONES LEON & RODAS LR-COMPTEL S.A.","CC":"EC","Users":32233,"Percent of CC Pop":0.28,"Percent of Internet":0.0008,"Samples":46003},
{"rank":29,"AS":267699,"Description":"CUBOTELECOM CIA. LTDA.","CC":"EC","Users":32224,"Percent of CC Pop":0.28,"Percent of Internet":0.0008,"Samples":45647},
{"rank":30,"AS":271933,"Description":"AIRMAXTELECOM SOLUCIONES TECNOLOGICAS S.A.","CC":"EC","Users":30937,"Percent of CC Pop":0.27,"Percent of Internet":0.0007,"Samples":43867},
{"rank":31,"AS":266894,"Description":"LOJASYSTEM C.A.","CC":"EC","Users":30538,"Percent of CC Pop":0.27,"Percent of Internet":0.0007,"Samples":43448},
{"rank":32,"AS":263805,"Description":"SOLUCIONES AVANZADAS INFORMATICAS Y TELECOMUNICACIONES SAITEL","CC":"EC","Users":30376,"Percent of CC Pop":0.27,"Percent of Internet":0.0007,"Samples":43070},
{"rank":33,"AS":272034,"Description":"ECUAFIBRA S.A.","CC":"EC","Users":30307,"Percent of CC Pop":0.27,"Percent of Internet":0.0007,"Samples":43480},
{"rank":34,"AS":263245,"Description":"CINECABLE TV","CC":"EC","Users":29952,"Percent of CC Pop":0.26,"Percent of Internet":0.0007,"Samples":42658},
{"rank":35,"AS":273966,"Description":"FIBERGO-TELECOM S.A.","CC":"EC","Users":29804,"Percent of CC Pop":0.26,"Percent of Internet":0.0007,"Samples":41521},
{"rank":36,"AS":269955,"Description":"ALFATV CABLE S.A","CC":"EC","Users":29474,"Percent of CC Pop":0.26,"Percent of Internet":0.0007,"Samples":41270},
{"rank":37,"AS":265711,"Description":"KOLVECH S.A. TELECOMVAS","CC":"EC","Users":28698,"Percent of CC Pop":0.25,"Percent of Internet":0.0007,"Samples":40454},
{"rank":38,"AS":266783,"Description":"Anibal Humberto Enriquez MoncayoComunicate","CC":"EC","Users":26936,"Percent of CC Pop":0.24,"Percent of Internet":0.0006,"Samples":37944},
{"rank":39,"AS":269936,"Description":"TELEVISION MONTALVO VISION MONVISION S.A.","CC":"EC","Users":26873,"Percent of CC Pop":0.24,"Percent of Internet":0.0006,"Samples":37929},
{"rank":40,"AS":273883,"Description":"MEGATEL-EC S.A.","CC":"EC","Users":26816,"Percent of CC Pop":0.24,"Percent of Internet":0.0006,"Samples":37794},
{"rank":41,"AS":271911,"Description":"Gavilanes Parreno Irene Del Rocio","CC":"EC","Users":26458,"Percent of CC Pop":0.23,"Percent of Internet":0.0006,"Samples":37466},
{"rank":42,"AS":266880,"Description":"BENALCAZAR ROMERO LEONARDO ISRAEL MAXXNET","CC":"EC","Users":26221,"Percent of CC Pop":0.23,"Percent of Internet":0.0006,"Samples":36880},
{"rank":43,"AS":266812,"Description":"CONEXIONTOTAL S.A.","CC":"EC","Users":24682,"Percent of CC Pop":0.22,"Percent of Internet":0.0006,"Samples":35240},
{"rank":44,"AS":265632,"Description":"ANGEL BENIGNO CONDOLO GUAYA","CC":"EC","Users":22382,"Percent of CC Pop":0.20,"Percent of Internet":0.0005,"Samples":30913},
{"rank":45,"AS":23031,"Description":"TELECU TELECOMUNICACIONES DEL ECUADOR TELECUSA S.A.S.","CC":"EC","Users":21729,"Percent of CC Pop":0.19,"Percent of Internet":0.0005,"Samples":30688},
{"rank":46,"AS":273123,"Description":"CRAMCOMNET CIA.LTDA.","CC":"EC","Users":20700,"Percent of CC Pop":0.18,"Percent of Internet":0.0005,"Samples":29349},
{"rank":47,"AS":61468,"Description":"CEDIA","CC":"EC","Users":20654,"Percent of CC Pop":0.18,"Percent of Internet":0.0005,"Samples":29346},
{"rank":48,"AS":271837,"Description":"DESPLIEGUE COMPUTACIONAL E INTERNET DCNET S.A.","CC":"EC","Users":20418,"Percent of CC Pop":0.18,"Percent of Internet":0.0005,"Samples":28994},
{"rank":49,"AS":271936,"Description":"SERVICIOS DE TELECOMUNICACIONES ATVCABLE CIA. LTDA.","CC":"EC","Users":19355,"Percent of CC Pop":0.17,"Percent of Internet":0.0005,"Samples":27252},
{"rank":50,"AS":273098,"Description":"BARREIRO MENENDEZ SILVIA BEATRIZ CABLE HOGAR","CC":"EC","Users":19257,"Percent of CC Pop":0.17,"Percent of Internet":0.0005,"Samples":27176},
{"rank":51,"AS":266802,"Description":"CODGREC S.A.","CC":"EC","Users":19151,"Percent of CC Pop":0.17,"Percent of Internet":0.0005,"Samples":27249},
{"rank":52,"AS":267916,"Description":"AGUILAR AGUILAR ASOCIADOS Y COMPANIA","CC":"EC","Users":18764,"Percent of CC Pop":0.17,"Percent of Internet":0.0004,"Samples":26720},
{"rank":53,"AS":265762,"Description":"CASTRO TELLO MARCO IVAN CONEXION GLOBAL","CC":"EC","Users":17884,"Percent of CC Pop":0.16,"Percent of Internet":0.0004,"Samples":25418},
{"rank":54,"AS":272954,"Description":"VUELATECHNOLOGY S.A.S.","CC":"EC","Users":17663,"Percent of CC Pop":0.16,"Percent of Internet":0.0004,"Samples":25246},
{"rank":55,"AS":270071,"Description":"SIGNAL-TELECOM TELECOMUNICACIONES & T.I CIA.LTDA.","CC":"EC","Users":17555,"Percent of CC Pop":0.15,"Percent of Internet":0.0004,"Samples":24864},
{"rank":56,"AS":273142,"Description":"SERVICIOS DE TELCOMUNICACIONES LATEVECOM CIA LTDA","CC":"EC","Users":17043,"Percent of CC Pop":0.15,"Percent of Internet":0.0004,"Samples":23874},
{"rank":57,"AS":269953,"Description":"SMART TECHNOLOGY S.A. TECHSMART","CC":"EC","Users":16637,"Percent of CC Pop":0.15,"Percent of Internet":0.0004,"Samples":23489},
{"rank":58,"AS":266834,"Description":"INSTALACION DE SISTEMAS EN REDES INSYSRED S.A.","CC":"EC","Users":16395,"Percent of CC Pop":0.14,"Percent of Internet":0.0004,"Samples":23269},
{"rank":59,"AS":273832,"Description":"GAVILANEZ PROANO PAOLA ALEXANDRA","CC":"EC","Users":15954,"Percent of CC Pop":0.14,"Percent of Internet":0.0004,"Samples":22622},
{"rank":60,"AS":271822,"Description":"INNO FIBER INFI CIA LTDA","CC":"EC","Users":15624,"Percent of CC Pop":0.14,"Percent of Internet":0.0004,"Samples":22000},
{"rank":61,"AS":3549,"Description":"LVLT-3549 - Level 3 Parent, LLC","CC":"EC","Users":15444,"Percent of CC Pop":0.14,"Percent of Internet":0.0004,"Samples":21917},
{"rank":62,"AS":269852,"Description":"LOJANOS TELECOMUNICACIONES ASTRONETV CIA. LTDA","CC":"EC","Users":14864,"Percent of CC Pop":0.13,"Percent of Internet":0.0004,"Samples":20950},
{"rank":63,"AS":272883,"Description":"BRITEL S.A.","CC":"EC","Users":14835,"Percent of CC Pop":0.13,"Percent of Internet":0.0004,"Samples":20943},
{"rank":64,"AS":269806,"Description":"PEREZ TITO JULIO CESARFASTNETT","CC":"EC","Users":14498,"Percent of CC Pop":0.13,"Percent of Internet":0.0003,"Samples":20654},
{"rank":65,"AS":265657,"Description":"SERVICABLE CIA. LTDA.","CC":"EC","Users":14146,"Percent of CC Pop":0.12,"Percent of Internet":0.0003,"Samples":20078},
{"rank":66,"AS":274252,"Description":"ORELTELECOM S.A.S.","CC":"EC","Users":14081,"Percent of CC Pop":0.12,"Percent of Internet":0.0003,"Samples":865},
{"rank":67,"AS":265724,"Description":"Teneda Corporacion CIA. LTDA","CC":"EC","Users":13669,"Percent of CC Pop":0.12,"Percent of Internet":0.0003,"Samples":19287},
{"rank":68,"AS":272097,"Description":"TELEVISION POR CABLE COCATEVE S.A. GRUPO COCAVISION","CC":"EC","Users":13510,"Percent of CC Pop":0.12,"Percent of Internet":0.0003,"Samples":18902},
{"rank":69,"AS":272817,"Description":"SPEED FIBER SPEEDFIBER CIA.LTDA.","CC":"EC","Users":13058,"Percent of CC Pop":0.11,"Percent of Internet":0.0003,"Samples":18458},
{"rank":70,"AS":264824,"Description":"COMPANIA ELECTROMECANICOS PARA EL DESARROLLO CSED SA","CC":"EC","Users":13019,"Percent of CC Pop":0.11,"Percent of Internet":0.0003,"Samples":18460},
{"rank":71,"AS":272827,"Description":"AMMAZONTVNET CIA.LTDA.","CC":"EC","Users":12957,"Percent of CC Pop":0.11,"Percent of Internet":0.0003,"Samples":18361},
{"rank":72,"AS":264836,"Description":"Asociacion de Proveedores de Servicio de Valor AgregadoAPROSVA","CC":"EC","Users":12825,"Percent of CC Pop":0.11,"Percent of Internet":0.0003,"Samples":18086},
{"rank":73,"AS":273068,"Description":"DIAZ TORO JAVIER ANDRES ECUARED PCTRONIC","CC":"EC","Users":12403,"Percent of CC Pop":0.11,"Percent of Internet":0.0003,"Samples":17445},
{"rank":74,"AS":264744,"Description":"WIFITELECOM","CC":"EC","Users":12309,"Percent of CC Pop":0.11,"Percent of Internet":0.0003,"Samples":17473},
{"rank":75,"AS":272094,"Description":"OPTILINK CIA LTDA","CC":"EC","Users":11544,"Percent of CC Pop":0.10,"Percent of Internet":0.0003,"Samples":16144},
{"rank":76,"AS":267778,"Description":"LAGONET-TV CIA. LTDA.","CC":"EC","Users":11530,"Percent of CC Pop":0.10,"Percent of Internet":0.0003,"Samples":16381},
{"rank":77,"AS":272147,"Description":"ZAMBRANO INTRIAGO RICHARD EDISSON ZAM NET","CC":"EC","Users":11347,"Percent of CC Pop":0.10,"Percent of Internet":0.0003,"Samples":16128},
{"rank":78,"AS":271785,"Description":"TELECOMUNICACIONES NETHOME CIA.LTDA.","CC":"EC","Users":11116,"Percent of CC Pop":0.10,"Percent of Internet":0.0003,"Samples":15604},
{"rank":79,"AS":272877,"Description":"TVDATOS S.C.C","CC":"EC","Users":11051,"Percent of CC Pop":0.10,"Percent of Internet":0.0003,"Samples":15462},
{"rank":80,"AS":271923,"Description":"ZOENETV S.A.","CC":"EC","Users":10631,"Percent of CC Pop":0.09,"Percent of Internet":0.0003,"Samples":15036},
{"rank":81,"AS":270016,"Description":"ALAVA MACAS GALO ALFREDO AIRNET","CC":"EC","Users":10117,"Percent of CC Pop":0.09,"Percent of Internet":0.0002,"Samples":14075},
{"rank":82,"AS":270009,"Description":"GUALAN JAPON LUIS JOAQUIN SARAGUROSNET","CC":"EC","Users":9895,"Percent of CC Pop":0.09,"Percent of Internet":0.0002,"Samples":13689},
{"rank":83,"AS":264746,"Description":"Maria Teresa Vivar CITYCOM","CC":"EC","Users":9721,"Percent of CC Pop":0.09,"Percent of Internet":0.0002,"Samples":14041},
{"rank":84,"AS":266667,"Description":"TECHNOLOGY EQUINOCCIAL TECCIAL S.A.","CC":"EC","Users":9433,"Percent of CC Pop":0.08,"Percent of Internet":0.0002,"Samples":13231},
{"rank":85,"AS":272939,"Description":"TELECOMNET S.A.","CC":"EC","Users":9414,"Percent of CC Pop":0.08,"Percent of Internet":0.0002,"Samples":13453},
{"rank":86,"AS":273190,"Description":"VASQUEZ BURGOS LIVINGTON","CC":"EC","Users":9289,"Percent of CC Pop":0.08,"Percent of Internet":0.0002,"Samples":13146},
{"rank":87,"AS":269728,"Description":"DECERET CIA. LTDA.","CC":"EC","Users":9085,"Percent of CC Pop":0.08,"Percent of Internet":0.0002,"Samples":12793},
{"rank":88,"AS":273141,"Description":"MICARMITA S.A.S","CC":"EC","Users":8678,"Percent of CC Pop":0.08,"Percent of Internet":0.0002,"Samples":12172},
{"rank":89,"AS":272019,"Description":"NETDIGITAL S.A.","CC":"EC","Users":8575,"Percent of CC Pop":0.08,"Percent of Internet":0.0002,"Samples":12075},
{"rank":90,"AS":27757,"Description":"CORPORACION NACIONAL DE TELECOMUNICACIONES - CNT EP","CC":"EC","Users":8162,"Percent of CC Pop":0.07,"Percent of Internet":0.0002,"Samples":10882},
{"rank":91,"AS":270095,"Description":"SALAZAR GUEVARA ELVIS XAVIER CABLE MAGICO","CC":"EC","Users":7896,"Percent of CC Pop":0.07,"Percent of Internet":0.0002,"Samples":10985},
{"rank":92,"AS":265815,"Description":"ESMONSA S.A.","CC":"EC","Users":7656,"Percent of CC Pop":0.07,"Percent of Internet":0.0002,"Samples":10618},
{"rank":93,"AS":271873,"Description":"ZAIGOVER S.A","CC":"EC","Users":7523,"Percent of CC Pop":0.07,"Percent of Internet":0.0002,"Samples":10659},
{"rank":94,"AS":3356,"Description":"LEVEL3 - Level 3 Parent, LLC","CC":"EC","Users":7452,"Percent of CC Pop":0.07,"Percent of Internet":0.0002,"Samples":10762},
{"rank":95,"AS":265863,"Description":"JEA.PC COMUNICACIONES S.A.","CC":"EC","Users":7242,"Percent of CC Pop":0.06,"Percent of Internet":0.0002,"Samples":10137},
{"rank":96,"AS":266664,"Description":"ADEATEL S.A","CC":"EC","Users":7053,"Percent of CC Pop":0.06,"Percent of Internet":0.0002,"Samples":10032},
{"rank":97,"AS":272914,"Description":"FAJARDO PILICITA NESTOR MARCELO JAKFIBER","CC":"EC","Users":6858,"Percent of CC Pop":0.06,"Percent of Internet":0.0002,"Samples":9684},
{"rank":98,"AS":264826,"Description":"POWERNET SD CIA. LTDA.","CC":"EC","Users":6795,"Percent of CC Pop":0.06,"Percent of Internet":0.0002,"Samples":9575},
{"rank":99,"AS":271967,"Description":"TURBONET S.A.","CC":"EC","Users":6590,"Percent of CC Pop":0.06,"Percent of Internet":0.0002,"Samples":5324},
{"rank":100,"AS":270100,"Description":"DRIVERNET S.A.","CC":"EC","Users":6266,"Percent of CC Pop":0.06,"Percent of Internet":0.0002,"Samples":8820},
{"rank":101,"AS":10753,"Description":"LUMEN-LEGACY-L3-CUSTOMER-SHARED-USE - Level 3 Parent, LLC","CC":"EC","Users":6258,"Percent of CC Pop":0.06,"Percent of Internet":0.0001,"Samples":8318},
{"rank":102,"AS":265787,"Description":"MERCREDI S.A.","CC":"EC","Users":6177,"Percent of CC Pop":0.05,"Percent of Internet":0.0001,"Samples":8801},
{"rank":103,"AS":264851,"Description":"IFOTONCORP S.A.","CC":"EC","Users":5640,"Percent of CC Pop":0.05,"Percent of Internet":0.0001,"Samples":7985},
{"rank":104,"AS":272075,"Description":"APOLO CHAMBA DAYRI NATHALIA RED PLUS","CC":"EC","Users":5609,"Percent of CC Pop":0.05,"Percent of Internet":0.0001,"Samples":7952},
{"rank":105,"AS":27740,"Description":"EDGEUNO ECUADOR S.A.","CC":"EC","Users":5488,"Percent of CC Pop":0.05,"Percent of Internet":0.0001,"Samples":7357},
{"rank":106,"AS":273923,"Description":"SPEEDNET-EC S.A.","CC":"EC","Users":5467,"Percent of CC Pop":0.05,"Percent of Internet":0.0001,"Samples":7632},
{"rank":107,"AS":271975,"Description":"CABRERA VELEZ ELIO DAVID","CC":"EC","Users":5343,"Percent of CC Pop":0.05,"Percent of Internet":0.0001,"Samples":7539},
{"rank":108,"AS":271840,"Description":"JOFRE HOMERO PACHECO PROANO","CC":"EC","Users":5299,"Percent of CC Pop":0.05,"Percent of Internet":0.0001,"Samples":7601},
{"rank":109,"AS":272998,"Description":"WORLD SISTEM TELECOM WST S.A.S.","CC":"EC","Users":5284,"Percent of CC Pop":0.05,"Percent of Internet":0.0001,"Samples":7379},
{"rank":110,"AS":263243,"Description":"BRIDGE TELECOM S.A.","CC":"EC","Users":5047,"Percent of CC Pop":0.04,"Percent of Internet":0.0001,"Samples":7143},
{"rank":111,"AS":273035,"Description":"CORPORACION LORIATELECOM S.A.S.","CC":"EC","Users":4891,"Percent of CC Pop":0.04,"Percent of Internet":0.0001,"Samples":6867},
{"rank":112,"AS":273233,"Description":"URBANO URBANO LUCIA DEL SOCORRO FIBERCOM ECUADOR","CC":"EC","Users":4871,"Percent of CC Pop":0.04,"Percent of Internet":0.0001,"Samples":6986},
{"rank":113,"AS":272823,"Description":"SILVA CORRALES DANIEL FERNANDO SMARTNET","CC":"EC","Users":4796,"Percent of CC Pop":0.04,"Percent of Internet":0.0001,"Samples":6890},
{"rank":114,"AS":265838,"Description":"TELECOM","CC":"EC","Users":4762,"Percent of CC Pop":0.04,"Percent of Internet":0.0001,"Samples":6716},
{"rank":115,"AS":266756,"Description":"EBESTPHONE ECUADOR S.A.","CC":"EC","Users":4642,"Percent of CC Pop":0.04,"Percent of Internet":0.0001,"Samples":6526},
{"rank":116,"AS":271882,"Description":"LLANOS ALOMIA LIGIA VERONICA","CC":"EC","Users":4554,"Percent of CC Pop":0.04,"Percent of Internet":0.0001,"Samples":6504},
{"rank":117,"AS":262169,"Description":"SOLINTELSA","CC":"EC","Users":4454,"Percent of CC Pop":0.04,"Percent of Internet":0.0001,"Samples":6212},
{"rank":118,"AS":273177,"Description":"TELECOM3000 S.A.","CC":"EC","Users":4435,"Percent of CC Pop":0.04,"Percent of Internet":0.0001,"Samples":6261},
{"rank":119,"AS":272121,"Description":"MONTANO VELEZ MARIA TERESA VISIONNET","CC":"EC","Users":4365,"Percent of CC Pop":0.04,"Percent of Internet":0.0001,"Samples":6081},
{"rank":120,"AS":266672,"Description":"SYSNOVELLTEL S.A","CC":"EC","Users":4274,"Percent of CC Pop":0.04,"Percent of Internet":0.0001,"Samples":6070},
{"rank":121,"AS":266867,"Description":"WILSON FERNANDO GOMEZ BARRIONUEVO","CC":"EC","Users":4171,"Percent of CC Pop":0.04,"Percent of Internet":0.0001,"Samples":5840},
{"rank":122,"AS":272889,"Description":"URDATEL S.A.S.","CC":"EC","Users":4124,"Percent of CC Pop":0.04,"Percent of Internet":0.0001,"Samples":5396},
{"rank":123,"AS":267849,"Description":"RECOMDATA CIA.LTDA.","CC":"EC","Users":4111,"Percent of CC Pop":0.04,"Percent of Internet":0.0001,"Samples":5817},
{"rank":124,"AS":274144,"Description":"TELINCOM S.A.","CC":"EC","Users":3875,"Percent of CC Pop":0.03,"Percent of Internet":0.0001,"Samples":4316},
{"rank":125,"AS":267787,"Description":"MENDOZA MENDOZA CARLOS ALFREDOTECGLO TECNOLOGIA GLOBAL","CC":"EC","Users":3647,"Percent of CC Pop":0.03,"Percent of Internet":0.0001,"Samples":5107},
{"rank":126,"AS":272032,"Description":"SITERTL CIA. LTDA.","CC":"EC","Users":3558,"Percent of CC Pop":0.03,"Percent of Internet":0.0001,"Samples":4984},
{"rank":127,"AS":271941,"Description":"NUNEZ DE LA ROSA RICHARD DALTON ECONTEL ECUADOR","CC":"EC","Users":3496,"Percent of CC Pop":0.03,"Percent of Internet":0.0001,"Samples":5000},
{"rank":128,"AS":269935,"Description":"TAPIA FLORES OSCAR ALDO FIBRANET ZAMORA","CC":"EC","Users":3241,"Percent of CC Pop":0.03,"Percent of Internet":0.0001,"Samples":4674},
{"rank":129,"AS":273140,"Description":"TELECOMUNICACIONES DEL ORIENTE TELECORPVP S.A.S.","CC":"EC","Users":3189,"Percent of CC Pop":0.03,"Percent of Internet":0.0001,"Samples":4573},
{"rank":130,"AS":274169,"Description":"TELECOMUNICACIONES SIERRA NETWORKS SIERRANET CIA.LTDA.","CC":"EC","Users":3150,"Percent of CC Pop":0.03,"Percent of Internet":0.0001,"Samples":781},
{"rank":131,"AS":273877,"Description":"TELECOMUNICACIONES NETHOMEMANTA S.A.S.","CC":"EC","Users":2696,"Percent of CC Pop":0.02,"Percent of Internet":0.0001,"Samples":3936},
{"rank":132,"AS":265775,"Description":"AUSTRONET","CC":"EC","Users":2646,"Percent of CC Pop":0.02,"Percent of Internet":0.0001,"Samples":3669},
{"rank":133,"AS":265629,"Description":"FIBERNET","CC":"EC","Users":2465,"Percent of CC Pop":0.02,"Percent of Internet":0.0001,"Samples":3506},
{"rank":134,"AS":269992,"Description":"Universidad de Guayaquil","CC":"EC","Users":2233,"Percent of CC Pop":0.02,"Percent of Internet":0.0001,"Samples":2612},
{"rank":135,"AS":272936,"Description":"CIDEMS CIA.LTDA.","CC":"EC","Users":1954,"Percent of CC Pop":0.02,"Percent of Internet":0.0000,"Samples":2729},
{"rank":136,"AS":273219,"Description":"EQUTECHS S.A.","CC":"EC","Users":1867,"Percent of CC Pop":0.02,"Percent of Internet":0.0000,"Samples":2605},
{"rank":137,"AS":269825,"Description":"UNIVERSIDAD DE LAS AMERICAS","CC":"EC","Users":1859,"Percent of CC Pop":0.02,"Percent of Internet":0.0000,"Samples":1502},
{"rank":138,"AS":266790,"Description":"GARCIA VILLAMAR ASOCIADOS CIA. LTDA. MUNDO WIRELESS","CC":"EC","Users":1854,"Percent of CC Pop":0.02,"Percent of Internet":0.0000,"Samples":2607},
{"rank":139,"AS":266839,"Description":"QUIMBITA PANCHI LUIS ANIBAL SISCOM","CC":"EC","Users":1810,"Percent of CC Pop":0.02,"Percent of Internet":0.0000,"Samples":2546},
{"rank":140,"AS":266856,"Description":"BRAVO BARAHONA WILLIAM ALBERTONUBESMART","CC":"EC","Users":1808,"Percent of CC Pop":0.02,"Percent of Internet":0.0000,"Samples":2570},
{"rank":141,"AS":269791,"Description":"ESCUELA SUPERIOR POLITECNICA DE CHIMBORAZO","CC":"EC","Users":1637,"Percent of CC Pop":0.01,"Percent of Internet":0.0000,"Samples":1700},
{"rank":142,"AS":13335,"Description":"CLOUDFLARENET - Cloudflare, Inc.","CC":"EC","Users":1607,"Percent of CC Pop":0.01,"Percent of Internet":0.0000,"Samples":2340},
{"rank":143,"AS":269790,"Description":"UNIVERSIDAD CATOLICA DE CUENCA","CC":"EC","Users":1535,"Percent of CC Pop":0.01,"Percent of Internet":0.0000,"Samples":1852},
{"rank":144,"AS":266728,"Description":"INTER&INTER S.A.","CC":"EC","Users":1482,"Percent of CC Pop":0.01,"Percent of Internet":0.0000,"Samples":2092},
{"rank":145,"AS":27948,"Description":"CORPORACION NACIONAL DE TELECOMUNICACIONES - CNT EP","CC":"EC","Users":1468,"Percent of CC Pop":0.01,"Percent of Internet":0.0000,"Samples":1627},
{"rank":146,"AS":270074,"Description":"UNIVERSIDAD DE LAS ARTES","CC":"EC","Users":1441,"Percent of CC Pop":0.01,"Percent of Internet":0.0000,"Samples":904},
{"rank":147,"AS":269761,"Description":"CAVNET S.A.","CC":"EC","Users":1410,"Percent of CC Pop":0.01,"Percent of Internet":0.0000,"Samples":2026},
{"rank":148,"AS":266681,"Description":"ZORRILLA SOLEDISPA JUAN JOBINO JJ COMP","CC":"EC","Users":1404,"Percent of CC Pop":0.01,"Percent of Internet":0.0000,"Samples":1905},
{"rank":149,"AS":269844,"Description":"UNIVERSIDAD NACIONAL DEL CHIMBORAZO","CC":"EC","Users":1404,"Percent of CC Pop":0.01,"Percent of Internet":0.0000,"Samples":1118},
{"rank":150,"AS":136787,"Description":"PACKETHUBSA-AS-AP PacketHub S.A.","CC":"EC","Users":1309,"Percent of CC Pop":0.01,"Percent of Internet":0.0000,"Samples":1710},
{"rank":151,"AS":265705,"Description":"HUGHES DE COLOMBIA S.A.S.","CC":"EC","Users":1301,"Percent of CC Pop":0.01,"Percent of Internet":0.0000,"Samples":1877},
{"rank":152,"AS":262212,"Description":"Escuela Politecnica Nacional","CC":"EC","Users":1144,"Percent of CC Pop":0.01,"Percent of Internet":0.0000,"Samples":1360},
{"rank":153,"AS":273163,"Description":"CABASCANGO FARINANGO MARIA ERLINDA","CC":"EC","Users":1128,"Percent of CC Pop":0.01,"Percent of Internet":0.0000,"Samples":1592},
{"rank":154,"AS":174,"Description":"COGENT-174 - Cogent Communications, LLC","CC":"EC","Users":1102,"Percent of CC Pop":0.01,"Percent of Internet":0.0000,"Samples":47},
{"rank":155,"AS":272819,"Description":"BOSCONET S.A.S.","CC":"EC","Users":1062,"Percent of CC Pop":0.01,"Percent of Internet":0.0000,"Samples":1440},
{"rank":156,"AS":28027,"Description":"Escuela Superior Politecnica del Litoral","CC":"EC","Users":1032,"Percent of CC Pop":0.01,"Percent of Internet":0.0000,"Samples":1070},
{"rank":157,"AS":52343,"Description":"UNIVERSIDAD UTE","CC":"EC","Users":935,"Percent of CC Pop":0.01,"Percent of Internet":0.0000,"Samples":668},
{"rank":158,"AS":274063,"Description":"RIMTEL S.A.S.","CC":"EC","Users":912,"Percent of CC Pop":0.01,"Percent of Internet":0.0000,"Samples":703},
{"rank":159,"AS":269805,"Description":"MEDIA COMMERCE MEDCOMM S.A","CC":"EC","Users":875,"Percent of CC Pop":0.01,"Percent of Internet":0.0000,"Samples":1210},
{"rank":160,"AS":270092,"Description":"ZAMBRANO CARRENO HUMBERTO ALEJANDRO PROGRAMAX","CC":"EC","Users":865,"Percent of CC Pop":0.01,"Percent of Internet":0.0000,"Samples":1174},
{"rank":161,"AS":137409,"Description":"GSLNETWORKS-AS-AP GSL Networks Pty LTD","CC":"EC","Users":815,"Percent of CC Pop":0.01,"Percent of Internet":0.0000,"Samples":767},
{"rank":162,"AS":267924,"Description":"BRAVO MEDRANO JOSE LUIS ECUABIT INTERNET","CC":"EC","Users":763,"Percent of CC Pop":0.01,"Percent of Internet":0.0000,"Samples":945},
{"rank":163,"AS":272140,"Description":"UNIVERSIDAD DE INVESTIGACION DE TECNOLOGIA EXPERIMENTAL YACHAY","CC":"EC","Users":720,"Percent of CC Pop":0.01,"Percent of Internet":0.0000,"Samples":628},
{"rank":164,"AS":273951,"Description":"PASTAZATV S.A.","CC":"EC","Users":696,"Percent of CC Pop":0.01,"Percent of Internet":0.0000,"Samples":630},
{"rank":165,"AS":263812,"Description":"SONDATECH S.A.S.","CC":"EC","Users":691,"Percent of CC Pop":0.01,"Percent of Internet":0.0000,"Samples":848},
{"rank":166,"AS":27902,"Description":"GPF CORPORACION - POWERFAST","CC":"EC","Users":690,"Percent of CC Pop":0.01,"Percent of Internet":0.0000,"Samples":889},
{"rank":167,"AS":274004,"Description":"NAVARRETE HIDALGO EDISON JESUS","CC":"EC","Users":675,"Percent of CC Pop":0.01,"Percent of Internet":0.0000,"Samples":751},
{"rank":168,"AS":269792,"Description":"UNIVERSIDAD TECNOLOGICA INDOAMERICA","CC":"EC","Users":667,"Percent of CC Pop":0.01,"Percent of Internet":0.0000,"Samples":742},
{"rank":169,"AS":28058,"Description":"Stealth Telecom del Ecuador","CC":"EC","Users":666,"Percent of CC Pop":0.01,"Percent of Internet":0.0000,"Samples":864},
{"rank":170,"AS":52458,"Description":"WISP INTERNET ECUADOR","CC":"EC","Users":651,"Percent of CC Pop":0.01,"Percent of Internet":0.0000,"Samples":856},
{"rank":171,"AS":262154,"Description":"Comm & Net S.A.","CC":"EC","Users":554,"Percent of CC Pop":0.00,"Percent of Internet":0.0000,"Samples":670},
{"rank":172,"AS":197991,"Description":"HISPASAT","CC":"EC","Users":540,"Percent of CC Pop":0.00,"Percent of Internet":0.0000,"Samples":659},
{"rank":173,"AS":209854,"Description":"CYBERZONEHUB","CC":"EC","Users":465,"Percent of CC Pop":0.00,"Percent of Internet":0.0000,"Samples":419},
{"rank":174,"AS":264788,"Description":"Telconet S.A","CC":"EC","Users":461,"Percent of CC Pop":0.00,"Percent of Internet":0.0000,"Samples":60},
{"rank":175,"AS":136258,"Description":"ONEPROVIDER-AS BrainStorm Network, Inc","CC":"EC","Users":446,"Percent of CC Pop":0.00,"Percent of Internet":0.0000,"Samples":420},
{"rank":176,"AS":272080,"Description":"Universidad Estatal de Milagro","CC":"EC","Users":441,"Percent of CC Pop":0.00,"Percent of Internet":0.0000,"Samples":404},
{"rank":177,"AS":267881,"Description":"SAOREDES CIA. LTDA. SAOHOSTING","CC":"EC","Users":408,"Percent of CC Pop":0.00,"Percent of Internet":0.0000,"Samples":83},
{"rank":178,"AS":272067,"Description":"Universidad Estatal de Bolivar","CC":"EC","Users":401,"Percent of CC Pop":0.00,"Percent of Internet":0.0000,"Samples":192},
{"rank":179,"AS":394089,"Description":"GCP-ENTERPRISE-USER-TRAFFIC - Google LLC","CC":"EC","Users":399,"Percent of CC Pop":0.00,"Percent of Internet":0.0000,"Samples":403},
{"rank":180,"AS":273839,"Description":"SMARTCONEXION CIA.LTDA.","CC":"EC","Users":392,"Percent of CC Pop":0.00,"Percent of Internet":0.0000,"Samples":128},
{"rank":181,"AS":273127,"Description":"VITERI HERNANDEZ CHRYSTIAN PATRICIO","CC":"EC","Users":380,"Percent of CC Pop":0.00,"Percent of Internet":0.0000,"Samples":346},
{"rank":182,"AS":23246,"Description":"gigaipnet.com Inc","CC":"EC","Users":358,"Percent of CC Pop":0.00,"Percent of Internet":0.0000,"Samples":384},
{"rank":183,"AS":212238,"Description":"CDNEXT","CC":"EC","Users":339,"Percent of CC Pop":0.00,"Percent of Internet":0.0000,"Samples":126},
{"rank":184,"AS":36183,"Description":"AKAMAI-AS - Akamai Technologies, Inc.","CC":"EC","Users":325,"Percent of CC Pop":0.00,"Percent of Internet":0.0000,"Samples":422},
{"rank":185,"AS":269941,"Description":"Universidad Particular de Especialidades Espiritu Santo","CC":"EC","Users":301,"Percent of CC Pop":0.00,"Percent of Internet":0.0000,"Samples":33},
{"rank":186,"AS":263174,"Description":"NOVANET","CC":"EC","Users":292,"Percent of CC Pop":0.00,"Percent of Internet":0.0000,"Samples":211},
{"rank":187,"AS":27998,"Description":"Contecon Guayaquil S.A.","CC":"EC","Users":247,"Percent of CC Pop":0.00,"Percent of Internet":0.0000,"Samples":13},
{"rank":188,"AS":271821,"Description":"UNIVERSIDAD TECNICA DEL NORTE","CC":"EC","Users":235,"Percent of CC Pop":0.00,"Percent of Internet":0.0000,"Samples":19},
{"rank":189,"AS":262287,"Description":"Latitude.sh LTDA","CC":"EC","Users":234,"Percent of CC Pop":0.00,"Percent of Internet":0.0000,"Samples":152},
{"rank":190,"AS":13150,"Description":"CATON","CC":"EC","Users":230,"Percent of CC Pop":0.00,"Percent of Internet":0.0000,"Samples":149},
{"rank":191,"AS":27820,"Description":"Universidad Tecnica Particular de Loja","CC":"EC","Users":227,"Percent of CC Pop":0.00,"Percent of Internet":0.0000,"Samples":128},
{"rank":192,"AS":27855,"Description":"AXESAT S.A","CC":"EC","Users":194,"Percent of CC Pop":0.00,"Percent of Internet":0.0000,"Samples":20},
{"rank":193,"AS":198605,"Description":"AVAST-AS-DC Gen Digital dba as Avast","CC":"EC","Users":185,"Percent of CC Pop":0.00,"Percent of Internet":0.0000,"Samples":29},
{"rank":194,"AS":27784,"Description":"Bco. Pichincha Matriz","CC":"EC","Users":175,"Percent of CC Pop":0.00,"Percent of Internet":0.0000,"Samples":96},
{"rank":195,"AS":7195,"Description":"EDGEUNO S.A.S","CC":"EC","Users":169,"Percent of CC Pop":0.00,"Percent of Internet":0.0000,"Samples":15},
{"rank":196,"AS":264801,"Description":"BANCO GUAYAQUIL","CC":"EC","Users":153,"Percent of CC Pop":0.00,"Percent of Internet":0.0000,"Samples":29},
{"rank":197,"AS":64110,"Description":"LK-TRO-KOM S.A. ELECTROCOM","CC":"EC","Users":131,"Percent of CC Pop":0.00,"Percent of Internet":0.0000,"Samples":36},
{"rank":198,"AS":132372,"Description":"GBNETWORK-AS-AP GB Network Solutions Sdn. Bhd.","CC":"EC","Users":125,"Percent of CC Pop":0.00,"Percent of Internet":0.0000,"Samples":15},
{"rank":199,"AS":54113,"Description":"FASTLY - Fastly, Inc.","CC":"EC","Users":118,"Percent of CC Pop":0.00,"Percent of Internet":0.0000,"Samples":68},
{"rank":200,"AS":203724,"Description":"MGG4-AS1 OCITOKEN::203724:96bdd83e28cd70a1d1f9b623bcbbf8c45708843daaaca2472da4cfd179c96b5b","CC":"EC","Users":116,"Percent of CC Pop":0.00,"Percent of Internet":0.0000,"Samples":29},
{"rank":201,"AS":55256,"Description":"NETSKOPE - Netskope Inc","CC":"EC","Users":112,"Percent of CC Pop":0.00,"Percent of Internet":0.0000,"Samples":40},
{"rank":202,"AS":262257,"Description":"Banco Bolivariano C.A.","CC":"EC","Users":110,"Percent of CC Pop":0.00,"Percent of Internet":0.0000,"Samples":12},
{"rank":203,"AS":28025,"Description":"CENTROSUR","CC":"EC","Users":101,"Percent of CC Pop":0.00,"Percent of Internet":0.0000,"Samples":21},
{"rank":204,"AS":9009,"Description":"M247","CC":"EC","Users":90,"Percent of CC Pop":0.00,"Percent of Internet":0.0000,"Samples":11}
  ]
}
