{
 "copyright": "(C) APNIC Pty/Ltd. Re-use with attribution permitted",
  "description": "Estimates of user population per AS",
  "Date": "28/04/2026",
  "Window": "120 Days",
 "Data": [
{"rank":1,"AS":2119,"Description":"TELENOR-NEXTEL Telenor Norge AS","CC":"NO","Users":1417374,"Percent of CC Pop":27.28,"Percent of Internet":0.0340,"Samples":1917940},
{"rank":2,"AS":29695,"Description":"ALTIBOX_AS Norway","CC":"NO","Users":1401660,"Percent of CC Pop":26.98,"Percent of Internet":0.0336,"Samples":1897561},
{"rank":3,"AS":25400,"Description":"TELIA-NORWAY-AS Telia Norway Core Networks","CC":"NO","Users":651742,"Percent of CC Pop":12.55,"Percent of Internet":0.0156,"Samples":896889},
{"rank":4,"AS":12929,"Description":"NETCOM-AS Oslo, Norway","CC":"NO","Users":332537,"Percent of CC Pop":6.40,"Percent of Internet":0.0080,"Samples":294595},
{"rank":5,"AS":2116,"Description":"GLOBALCONNECT-AS2116","CC":"NO","Users":229622,"Percent of CC Pop":4.42,"Percent of Internet":0.0055,"Samples":310935},
{"rank":6,"AS":34087,"Description":"NTE-BREDBAND NIX 1, Oslo, Norway","CC":"NO","Users":176563,"Percent of CC Pop":3.40,"Percent of Internet":0.0042,"Samples":237481},
{"rank":7,"AS":214875,"Description":"ALTIBOXAS Denmark","CC":"NO","Users":129047,"Percent of CC Pop":2.48,"Percent of Internet":0.0031,"Samples":170557},
{"rank":8,"AS":15659,"Description":"NEXTGENTEL NEXTGENTEL Autonomous System","CC":"NO","Users":110856,"Percent of CC Pop":2.13,"Percent of Internet":0.0027,"Samples":149181},
{"rank":9,"AS":203995,"Description":"ICENET","CC":"NO","Users":108637,"Percent of CC Pop":2.09,"Percent of Internet":0.0026,"Samples":145919},
{"rank":10,"AS":208172,"Description":"PV-HOSTED","CC":"NO","Users":79276,"Percent of CC Pop":1.53,"Percent of Internet":0.0019,"Samples":103806},
{"rank":11,"AS":56655,"Description":"GIGAHOST","CC":"NO","Users":75805,"Percent of CC Pop":1.46,"Percent of Internet":0.0018,"Samples":95658},
{"rank":12,"AS":211309,"Description":"OBOSOPENNET-","CC":"NO","Users":49043,"Percent of CC Pop":0.94,"Percent of Internet":0.0012,"Samples":66569},
{"rank":13,"AS":35132,"Description":"ENIVEST-AS","CC":"NO","Users":46199,"Percent of CC Pop":0.89,"Percent of Internet":0.0011,"Samples":62365},
{"rank":14,"AS":202204,"Description":"TROLLFJORD","CC":"NO","Users":39498,"Percent of CC Pop":0.76,"Percent of Internet":0.0009,"Samples":53258},
{"rank":15,"AS":206260,"Description":"SVORKA","CC":"NO","Users":37333,"Percent of CC Pop":0.72,"Percent of Internet":0.0009,"Samples":50143},
{"rank":16,"AS":203424,"Description":"TIKT","CC":"NO","Users":37196,"Percent of CC Pop":0.72,"Percent of Internet":0.0009,"Samples":50255},
{"rank":17,"AS":61275,"Description":"ASN-NEAS","CC":"NO","Users":34917,"Percent of CC Pop":0.67,"Percent of Internet":0.0008,"Samples":46751},
{"rank":18,"AS":49455,"Description":"UPC-AS","CC":"NO","Users":34479,"Percent of CC Pop":0.66,"Percent of Internet":0.0008,"Samples":46116},
{"rank":19,"AS":207137,"Description":"PACKETHUBSA","CC":"NO","Users":23856,"Percent of CC Pop":0.46,"Percent of Internet":0.0006,"Samples":8393},
{"rank":20,"AS":216374,"Description":"HARDANGERBREIBAND","CC":"NO","Users":20431,"Percent of CC Pop":0.39,"Percent of Internet":0.0005,"Samples":27438},
{"rank":21,"AS":212238,"Description":"CDNEXT","CC":"NO","Users":19832,"Percent of CC Pop":0.38,"Percent of Internet":0.0005,"Samples":26294},
{"rank":22,"AS":206557,"Description":"ELTELE","CC":"NO","Users":19413,"Percent of CC Pop":0.37,"Percent of Internet":0.0005,"Samples":26129},
{"rank":23,"AS":34989,"Description":"SERVETHEWORLD-AS","CC":"NO","Users":19127,"Percent of CC Pop":0.37,"Percent of Internet":0.0005,"Samples":23795},
{"rank":24,"AS":212449,"Description":"ERATE","CC":"NO","Users":18869,"Percent of CC Pop":0.36,"Percent of Internet":0.0005,"Samples":25354},
{"rank":25,"AS":31169,"Description":"SOGNENETT-AS Providing fiber and wireless access","CC":"NO","Users":17291,"Percent of CC Pop":0.33,"Percent of Internet":0.0004,"Samples":23052},
{"rank":26,"AS":16185,"Description":"RINGNETT-NORWAY RingNett AS Autonomous System","CC":"NO","Users":16942,"Percent of CC Pop":0.33,"Percent of Internet":0.0004,"Samples":22715},
{"rank":27,"AS":14593,"Description":"SPACEX-STARLINK - Space Exploration Technologies Corporation","CC":"NO","Users":15468,"Percent of CC Pop":0.30,"Percent of Internet":0.0004,"Samples":21091},
{"rank":28,"AS":9009,"Description":"M247","CC":"NO","Users":15013,"Percent of CC Pop":0.29,"Percent of Internet":0.0004,"Samples":11476},
{"rank":29,"AS":201596,"Description":"THREENETAS","CC":"NO","Users":14844,"Percent of CC Pop":0.29,"Percent of Internet":0.0004,"Samples":20102},
{"rank":30,"AS":224,"Description":"UNINETT UNINETT, The Norwegian University & Research Network","CC":"NO","Users":14588,"Percent of CC Pop":0.28,"Percent of Internet":0.0003,"Samples":19512},
{"rank":31,"AS":136787,"Description":"PACKETHUBSA-AS-AP PacketHub S.A.","CC":"NO","Users":14336,"Percent of CC Pop":0.28,"Percent of Internet":0.0003,"Samples":18905},
{"rank":32,"AS":43568,"Description":"VEV-ALO1","CC":"NO","Users":13406,"Percent of CC Pop":0.26,"Percent of Internet":0.0003,"Samples":17750},
{"rank":33,"AS":41111,"Description":"AS-GEOHOSTING","CC":"NO","Users":12777,"Percent of CC Pop":0.25,"Percent of Internet":0.0003,"Samples":651},
{"rank":34,"AS":60908,"Description":"SUCOM-AS","CC":"NO","Users":12508,"Percent of CC Pop":0.24,"Percent of Internet":0.0003,"Samples":17092},
{"rank":35,"AS":29492,"Description":"EIDSIVA-ASN","CC":"NO","Users":11800,"Percent of CC Pop":0.23,"Percent of Internet":0.0003,"Samples":15841},
{"rank":36,"AS":210150,"Description":"VOSSFIBER","CC":"NO","Users":11366,"Percent of CC Pop":0.22,"Percent of Internet":0.0003,"Samples":15189},
{"rank":37,"AS":212500,"Description":"SURFNET","CC":"NO","Users":11149,"Percent of CC Pop":0.21,"Percent of Internet":0.0003,"Samples":14719},
{"rank":38,"AS":31726,"Description":"TELEFIBER","CC":"NO","Users":10064,"Percent of CC Pop":0.19,"Percent of Internet":0.0002,"Samples":13819},
{"rank":39,"AS":29300,"Description":"AS-DIRECTCONNECT","CC":"NO","Users":8418,"Percent of CC Pop":0.16,"Percent of Internet":0.0002,"Samples":11465},
{"rank":40,"AS":56828,"Description":"NORWEGIANHEALTHNETWORK","CC":"NO","Users":8388,"Percent of CC Pop":0.16,"Percent of Internet":0.0002,"Samples":11050},
{"rank":41,"AS":200367,"Description":"NTENS-AS","CC":"NO","Users":8203,"Percent of CC Pop":0.16,"Percent of Internet":0.0002,"Samples":1190},
{"rank":42,"AS":263740,"Description":"Corporacion Laceibanetsociety","CC":"NO","Users":7774,"Percent of CC Pop":0.15,"Percent of Internet":0.0002,"Samples":5996},
{"rank":43,"AS":52157,"Description":"NONEAS-AS","CC":"NO","Users":7307,"Percent of CC Pop":0.14,"Percent of Internet":0.0002,"Samples":9792},
{"rank":44,"AS":5377,"Description":"MARLINK-EMEA","CC":"NO","Users":6736,"Percent of CC Pop":0.13,"Percent of Internet":0.0002,"Samples":8777},
{"rank":45,"AS":205016,"Description":"HERNLABS","CC":"NO","Users":6283,"Percent of CC Pop":0.12,"Percent of Internet":0.0002,"Samples":8145},
{"rank":46,"AS":200665,"Description":"HFESTENERGI","CC":"NO","Users":5808,"Percent of CC Pop":0.11,"Percent of Internet":0.0001,"Samples":7739},
{"rank":47,"AS":8542,"Description":"EVINY-AS8542 Norway","CC":"NO","Users":5770,"Percent of CC Pop":0.11,"Percent of Internet":0.0001,"Samples":7736},
{"rank":48,"AS":201577,"Description":"MONSTERNETT","CC":"NO","Users":5658,"Percent of CC Pop":0.11,"Percent of Internet":0.0001,"Samples":7529},
{"rank":49,"AS":58264,"Description":"LYSGLIMT","CC":"NO","Users":5608,"Percent of CC Pop":0.11,"Percent of Internet":0.0001,"Samples":7816},
{"rank":50,"AS":197212,"Description":"AARDALSNETT-AS","CC":"NO","Users":5333,"Percent of CC Pop":0.10,"Percent of Internet":0.0001,"Samples":7299},
{"rank":51,"AS":42708,"Description":"GLESYS glesys.com","CC":"NO","Users":4708,"Percent of CC Pop":0.09,"Percent of Internet":0.0001,"Samples":6262},
{"rank":52,"AS":48863,"Description":"RENROROSAKSESS","CC":"NO","Users":4323,"Percent of CC Pop":0.08,"Percent of Internet":0.0001,"Samples":5785},
{"rank":53,"AS":174,"Description":"COGENT-174 - Cogent Communications, LLC","CC":"NO","Users":4080,"Percent of CC Pop":0.08,"Percent of Internet":0.0001,"Samples":154},
{"rank":54,"AS":12552,"Description":"GLOBALCONNECT-AS12552","CC":"NO","Users":3736,"Percent of CC Pop":0.07,"Percent of Internet":0.0001,"Samples":4881},
{"rank":55,"AS":8896,"Description":"XFIBER-AS","CC":"NO","Users":3589,"Percent of CC Pop":0.07,"Percent of Internet":0.0001,"Samples":4706},
{"rank":56,"AS":50272,"Description":"AVUR AVUR","CC":"NO","Users":3385,"Percent of CC Pop":0.07,"Percent of Internet":0.0001,"Samples":4260},
{"rank":57,"AS":42175,"Description":"EQUINOR-AS","CC":"NO","Users":3106,"Percent of CC Pop":0.06,"Percent of Internet":0.0001,"Samples":4125},
{"rank":58,"AS":13335,"Description":"CLOUDFLARENET - Cloudflare, Inc.","CC":"NO","Users":3022,"Percent of CC Pop":0.06,"Percent of Internet":0.0001,"Samples":4092},
{"rank":59,"AS":50304,"Description":"BLIX","CC":"NO","Users":2941,"Percent of CC Pop":0.06,"Percent of Internet":0.0001,"Samples":3808},
{"rank":60,"AS":213043,"Description":"ATMCOM","CC":"NO","Users":2642,"Percent of CC Pop":0.05,"Percent of Internet":0.0001,"Samples":3454},
{"rank":61,"AS":136258,"Description":"ONEPROVIDER-AS BrainStorm Network, Inc","CC":"NO","Users":2625,"Percent of CC Pop":0.05,"Percent of Internet":0.0001,"Samples":3352},
{"rank":62,"AS":50217,"Description":"HFK-ASN","CC":"NO","Users":2404,"Percent of CC Pop":0.05,"Percent of Internet":0.0001,"Samples":2378},
{"rank":63,"AS":204996,"Description":"TMNET","CC":"NO","Users":2090,"Percent of CC Pop":0.04,"Percent of Internet":0.0001,"Samples":2781},
{"rank":64,"AS":15765,"Description":"MIMER","CC":"NO","Users":1882,"Percent of CC Pop":0.04,"Percent of Internet":0.0000,"Samples":2410},
{"rank":65,"AS":43905,"Description":"SPN-AS","CC":"NO","Users":1747,"Percent of CC Pop":0.03,"Percent of Internet":0.0000,"Samples":793},
{"rank":66,"AS":15169,"Description":"GOOGLE - Google LLC","CC":"NO","Users":1670,"Percent of CC Pop":0.03,"Percent of Internet":0.0000,"Samples":2131},
{"rank":67,"AS":215730,"Description":"H2NEXUS-AS H2NEXUS LTD","CC":"NO","Users":1634,"Percent of CC Pop":0.03,"Percent of Internet":0.0000,"Samples":1677},
{"rank":68,"AS":60278,"Description":"HELSE-VEST-IKT","CC":"NO","Users":1605,"Percent of CC Pop":0.03,"Percent of Internet":0.0000,"Samples":2154},
{"rank":69,"AS":206804,"Description":"ESTNOC-GLOBAL","CC":"NO","Users":1583,"Percent of CC Pop":0.03,"Percent of Internet":0.0000,"Samples":53},
{"rank":70,"AS":62044,"Description":"ZSCALER-EMEA","CC":"NO","Users":1567,"Percent of CC Pop":0.03,"Percent of Internet":0.0000,"Samples":1946},
{"rank":71,"AS":49586,"Description":"ASN-INTILITY","CC":"NO","Users":1547,"Percent of CC Pop":0.03,"Percent of Internet":0.0000,"Samples":1693},
{"rank":72,"AS":61006,"Description":"BREDBANDSFYLKET-TROMS","CC":"NO","Users":1542,"Percent of CC Pop":0.03,"Percent of Internet":0.0000,"Samples":1920},
{"rank":73,"AS":49278,"Description":"NORDEF","CC":"NO","Users":1442,"Percent of CC Pop":0.03,"Percent of Internet":0.0000,"Samples":1805},
{"rank":74,"AS":204503,"Description":"LUOSTEJOK","CC":"NO","Users":1322,"Percent of CC Pop":0.03,"Percent of Internet":0.0000,"Samples":1653},
{"rank":75,"AS":25148,"Description":"BASEFARM-ASN Oslo - Norway","CC":"NO","Users":1163,"Percent of CC Pop":0.02,"Percent of Internet":0.0000,"Samples":135},
{"rank":76,"AS":16186,"Description":"ASN-SSC","CC":"NO","Users":1125,"Percent of CC Pop":0.02,"Percent of Internet":0.0000,"Samples":1491},
{"rank":77,"AS":44431,"Description":"OMNIACCESS-AS","CC":"NO","Users":1116,"Percent of CC Pop":0.02,"Percent of Internet":0.0000,"Samples":1439},
{"rank":78,"AS":41869,"Description":"BLIXFIBER-AS Blix Fiber - FTTH","CC":"NO","Users":1106,"Percent of CC Pop":0.02,"Percent of Internet":0.0000,"Samples":1520},
{"rank":79,"AS":28795,"Description":"ELKEM-AS","CC":"NO","Users":1057,"Percent of CC Pop":0.02,"Percent of Internet":0.0000,"Samples":740},
{"rank":80,"AS":200915,"Description":"MRFK","CC":"NO","Users":1046,"Percent of CC Pop":0.02,"Percent of Internet":0.0000,"Samples":853},
{"rank":81,"AS":8075,"Description":"MICROSOFT-CORP-MSN-AS-BLOCK - Microsoft Corporation","CC":"NO","Users":1043,"Percent of CC Pop":0.02,"Percent of Internet":0.0000,"Samples":1230},
{"rank":82,"AS":21331,"Description":"OKDN-AS","CC":"NO","Users":1034,"Percent of CC Pop":0.02,"Percent of Internet":0.0000,"Samples":1333},
{"rank":83,"AS":59562,"Description":"SENSIO-AS","CC":"NO","Users":1013,"Percent of CC Pop":0.02,"Percent of Internet":0.0000,"Samples":426},
{"rank":84,"AS":30737,"Description":"SAFETY-AS","CC":"NO","Users":1004,"Percent of CC Pop":0.02,"Percent of Internet":0.0000,"Samples":202},
{"rank":85,"AS":201454,"Description":"UPHEADS","CC":"NO","Users":976,"Percent of CC Pop":0.02,"Percent of Internet":0.0000,"Samples":1009},
{"rank":86,"AS":50531,"Description":"ABAX","CC":"NO","Users":941,"Percent of CC Pop":0.02,"Percent of Internet":0.0000,"Samples":20},
{"rank":87,"AS":205190,"Description":"ALTAKRAFTLAG","CC":"NO","Users":938,"Percent of CC Pop":0.02,"Percent of Internet":0.0000,"Samples":1111},
{"rank":88,"AS":206145,"Description":"IKTORKIDE","CC":"NO","Users":930,"Percent of CC Pop":0.02,"Percent of Internet":0.0000,"Samples":896},
{"rank":89,"AS":207464,"Description":"VARANGERKRAFTUTVIKLING","CC":"NO","Users":894,"Percent of CC Pop":0.02,"Percent of Internet":0.0000,"Samples":669},
{"rank":90,"AS":208835,"Description":"INFRANORD","CC":"NO","Users":845,"Percent of CC Pop":0.02,"Percent of Internet":0.0000,"Samples":919},
{"rank":91,"AS":208966,"Description":"SKTV","CC":"NO","Users":830,"Percent of CC Pop":0.02,"Percent of Internet":0.0000,"Samples":997},
{"rank":92,"AS":211119,"Description":"RIGNET-NG-AS","CC":"NO","Users":805,"Percent of CC Pop":0.02,"Percent of Internet":0.0000,"Samples":425},
{"rank":93,"AS":55784,"Description":"AU-SYD-MARLINK-MSS MARLINK AU-SYD","CC":"NO","Users":791,"Percent of CC Pop":0.02,"Percent of Internet":0.0000,"Samples":308},
{"rank":94,"AS":36183,"Description":"AKAMAI-AS - Akamai Technologies, Inc.","CC":"NO","Users":784,"Percent of CC Pop":0.02,"Percent of Internet":0.0000,"Samples":1056},
{"rank":95,"AS":5619,"Description":"NO-TTSN-ASN1 TietoEVRY Norway","CC":"NO","Users":771,"Percent of CC Pop":0.01,"Percent of Internet":0.0000,"Samples":860},
{"rank":96,"AS":207957,"Description":"SERVHOST-AS","CC":"NO","Users":767,"Percent of CC Pop":0.01,"Percent of Internet":0.0000,"Samples":39},
{"rank":97,"AS":56538,"Description":"ASN-NETACCESS","CC":"NO","Users":765,"Percent of CC Pop":0.01,"Percent of Internet":0.0000,"Samples":49},
{"rank":98,"AS":7155,"Description":"VIASAT-SP-BACKBONE - ViaSat,Inc.","CC":"NO","Users":740,"Percent of CC Pop":0.01,"Percent of Internet":0.0000,"Samples":290},
{"rank":99,"AS":44123,"Description":"TELAVOX","CC":"NO","Users":736,"Percent of CC Pop":0.01,"Percent of Internet":0.0000,"Samples":867},
{"rank":100,"AS":203580,"Description":"NFK","CC":"NO","Users":736,"Percent of CC Pop":0.01,"Percent of Internet":0.0000,"Samples":607},
{"rank":101,"AS":41729,"Description":"ATEA-AOS-AS","CC":"NO","Users":712,"Percent of CC Pop":0.01,"Percent of Internet":0.0000,"Samples":577},
{"rank":102,"AS":200781,"Description":"TAMPNET-AS Tampnet International Carrier","CC":"NO","Users":707,"Percent of CC Pop":0.01,"Percent of Internet":0.0000,"Samples":632},
{"rank":103,"AS":39351,"Description":"ESAB-AS","CC":"NO","Users":705,"Percent of CC Pop":0.01,"Percent of Internet":0.0000,"Samples":344},
{"rank":104,"AS":215540,"Description":"GCS-AS","CC":"NO","Users":683,"Percent of CC Pop":0.01,"Percent of Internet":0.0000,"Samples":525},
{"rank":105,"AS":59720,"Description":"BOFIBER","CC":"NO","Users":665,"Percent of CC Pop":0.01,"Percent of Internet":0.0000,"Samples":781},
{"rank":106,"AS":6829,"Description":"NO-SOGNFJORDFYLKE Sogn og Fjordane County","CC":"NO","Users":631,"Percent of CC Pop":0.01,"Percent of Internet":0.0000,"Samples":493},
{"rank":107,"AS":49214,"Description":"GAULDALIKT-AS","CC":"NO","Users":615,"Percent of CC Pop":0.01,"Percent of Internet":0.0000,"Samples":564},
{"rank":108,"AS":8478,"Description":"ASN-GIGNETWORKS","CC":"NO","Users":611,"Percent of CC Pop":0.01,"Percent of Internet":0.0000,"Samples":588},
{"rank":109,"AS":213957,"Description":"LILLESTROM-KOMMUNE","CC":"NO","Users":589,"Percent of CC Pop":0.01,"Percent of Internet":0.0000,"Samples":607},
{"rank":110,"AS":8841,"Description":"US-NYC-MARLINK-MSS Marlink MSS division New York AS","CC":"NO","Users":586,"Percent of CC Pop":0.01,"Percent of Internet":0.0000,"Samples":583},
{"rank":111,"AS":44559,"Description":"ITHOSTLINE","CC":"NO","Users":579,"Percent of CC Pop":0.01,"Percent of Internet":0.0000,"Samples":29},
{"rank":112,"AS":208692,"Description":"ASN-NCIS","CC":"NO","Users":549,"Percent of CC Pop":0.01,"Percent of Internet":0.0000,"Samples":59},
{"rank":113,"AS":62225,"Description":"HALDENDATASERVICE","CC":"NO","Users":521,"Percent of CC Pop":0.01,"Percent of Internet":0.0000,"Samples":431},
{"rank":114,"AS":206897,"Description":"ASN-NO-STERIA","CC":"NO","Users":495,"Percent of CC Pop":0.01,"Percent of Internet":0.0000,"Samples":538},
{"rank":115,"AS":62002,"Description":"RISSAKRAFTLAG-AS","CC":"NO","Users":490,"Percent of CC Pop":0.01,"Percent of Internet":0.0000,"Samples":229},
{"rank":116,"AS":49788,"Description":"NEXTHOP","CC":"NO","Users":482,"Percent of CC Pop":0.01,"Percent of Internet":0.0000,"Samples":500},
{"rank":117,"AS":31264,"Description":"STIM-COMPUTING-AS Peering: peering@visolit.no","CC":"NO","Users":473,"Percent of CC Pop":0.01,"Percent of Internet":0.0000,"Samples":506},
{"rank":118,"AS":209965,"Description":"MULTINETT","CC":"NO","Users":467,"Percent of CC Pop":0.01,"Percent of Internet":0.0000,"Samples":29},
{"rank":119,"AS":394089,"Description":"GCP-ENTERPRISE-USER-TRAFFIC - Google LLC","CC":"NO","Users":460,"Percent of CC Pop":0.01,"Percent of Internet":0.0000,"Samples":477},
{"rank":120,"AS":22363,"Description":"PHMGMT-AS1 - Powerhouse Management, Inc.","CC":"NO","Users":450,"Percent of CC Pop":0.01,"Percent of Internet":0.0000,"Samples":72},
{"rank":121,"AS":208512,"Description":"RFNETT","CC":"NO","Users":438,"Percent of CC Pop":0.01,"Percent of Internet":0.0000,"Samples":151},
{"rank":122,"AS":20741,"Description":"ADMINISTRATOR","CC":"NO","Users":434,"Percent of CC Pop":0.01,"Percent of Internet":0.0000,"Samples":255},
{"rank":123,"AS":199990,"Description":"LOCALHOST_AS","CC":"NO","Users":428,"Percent of CC Pop":0.01,"Percent of Internet":0.0000,"Samples":37},
{"rank":124,"AS":43200,"Description":"PCSUPPORT","CC":"NO","Users":423,"Percent of CC Pop":0.01,"Percent of Internet":0.0000,"Samples":314},
{"rank":125,"AS":21067,"Description":"KANDU","CC":"NO","Users":421,"Percent of CC Pop":0.01,"Percent of Internet":0.0000,"Samples":21},
{"rank":126,"AS":60717,"Description":"BAYONETTE","CC":"NO","Users":415,"Percent of CC Pop":0.01,"Percent of Internet":0.0000,"Samples":338},
{"rank":127,"AS":57660,"Description":"COM4-AS","CC":"NO","Users":413,"Percent of CC Pop":0.01,"Percent of Internet":0.0000,"Samples":52},
{"rank":128,"AS":42675,"Description":"OBEHOSTING Obehosting AB","CC":"NO","Users":405,"Percent of CC Pop":0.01,"Percent of Internet":0.0000,"Samples":194},
{"rank":129,"AS":211443,"Description":"SINOWORLDWIDE","CC":"NO","Users":390,"Percent of CC Pop":0.01,"Percent of Internet":0.0000,"Samples":83},
{"rank":130,"AS":205238,"Description":"TIMEIT","CC":"NO","Users":389,"Percent of CC Pop":0.01,"Percent of Internet":0.0000,"Samples":28},
{"rank":131,"AS":206993,"Description":"AGDER-ENERGI-NORWAY","CC":"NO","Users":387,"Percent of CC Pop":0.01,"Percent of Internet":0.0000,"Samples":16},
{"rank":132,"AS":210314,"Description":"ITC-EU MARLINK-ITC, INC","CC":"NO","Users":382,"Percent of CC Pop":0.01,"Percent of Internet":0.0000,"Samples":174},
{"rank":133,"AS":49409,"Description":"IVERNORGE","CC":"NO","Users":373,"Percent of CC Pop":0.01,"Percent of Internet":0.0000,"Samples":173},
{"rank":134,"AS":49082,"Description":"ZONES-AS","CC":"NO","Users":368,"Percent of CC Pop":0.01,"Percent of Internet":0.0000,"Samples":131},
{"rank":135,"AS":42390,"Description":"THECLOUD-","CC":"NO","Users":355,"Percent of CC Pop":0.01,"Percent of Internet":0.0000,"Samples":109},
{"rank":136,"AS":206133,"Description":"CKE-AS","CC":"NO","Users":353,"Percent of CC Pop":0.01,"Percent of Internet":0.0000,"Samples":99},
{"rank":137,"AS":201656,"Description":"HKIT","CC":"NO","Users":348,"Percent of CC Pop":0.01,"Percent of Internet":0.0000,"Samples":69},
{"rank":138,"AS":28824,"Description":"ASN-EMPSECURE EMP Secure AS","CC":"NO","Users":345,"Percent of CC Pop":0.01,"Percent of Internet":0.0000,"Samples":230},
{"rank":139,"AS":21119,"Description":"WAN-","CC":"NO","Users":340,"Percent of CC Pop":0.01,"Percent of Internet":0.0000,"Samples":183},
{"rank":140,"AS":20868,"Description":"ABB IS Infrastructure & ServicesBS-ISI","CC":"NO","Users":337,"Percent of CC Pop":0.01,"Percent of Internet":0.0000,"Samples":128},
{"rank":141,"AS":197475,"Description":"ZNETT","CC":"NO","Users":335,"Percent of CC Pop":0.01,"Percent of Internet":0.0000,"Samples":16},
{"rank":142,"AS":212665,"Description":"SANDEFJORD-FIBER","CC":"NO","Users":335,"Percent of CC Pop":0.01,"Percent of Internet":0.0000,"Samples":254},
{"rank":143,"AS":201888,"Description":"CEGAL","CC":"NO","Users":329,"Percent of CC Pop":0.01,"Percent of Internet":0.0000,"Samples":164},
{"rank":144,"AS":202230,"Description":"NORSK-TIPPING","CC":"NO","Users":327,"Percent of CC Pop":0.01,"Percent of Internet":0.0000,"Samples":72},
{"rank":145,"AS":202057,"Description":"MOELVEN_NORDIA Moelven Industrier ASA","CC":"NO","Users":324,"Percent of CC Pop":0.01,"Percent of Internet":0.0000,"Samples":176},
{"rank":146,"AS":13150,"Description":"CATON","CC":"NO","Users":324,"Percent of CC Pop":0.01,"Percent of Internet":0.0000,"Samples":193},
{"rank":147,"AS":13243,"Description":"NO-TTSN-ASN2 Tietoevry Norway - Regions","CC":"NO","Users":322,"Percent of CC Pop":0.01,"Percent of Internet":0.0000,"Samples":180},
{"rank":148,"AS":205976,"Description":"INNIT","CC":"NO","Users":321,"Percent of CC Pop":0.01,"Percent of Internet":0.0000,"Samples":44},
{"rank":149,"AS":44933,"Description":"NL-AMS-MARLINK-MSS Marlink MSS NL AMS PoP","CC":"NO","Users":317,"Percent of CC Pop":0.01,"Percent of Internet":0.0000,"Samples":302},
{"rank":150,"AS":57829,"Description":"IVER","CC":"NO","Users":311,"Percent of CC Pop":0.01,"Percent of Internet":0.0000,"Samples":23},
{"rank":151,"AS":202128,"Description":"FJORDANE-IT","CC":"NO","Users":301,"Percent of CC Pop":0.01,"Percent of Internet":0.0000,"Samples":63},
{"rank":152,"AS":21293,"Description":"ASN-NRK NRK Autonomous System","CC":"NO","Users":300,"Percent of CC Pop":0.01,"Percent of Internet":0.0000,"Samples":197},
{"rank":153,"AS":26383,"Description":"ASNET - Baxet Group Inc.","CC":"NO","Users":299,"Percent of CC Pop":0.01,"Percent of Internet":0.0000,"Samples":52},
{"rank":154,"AS":38990,"Description":"AGNITIO-AS","CC":"NO","Users":299,"Percent of CC Pop":0.01,"Percent of Internet":0.0000,"Samples":47},
{"rank":155,"AS":209980,"Description":"MARLINK-EU-OMNIACCESS","CC":"NO","Users":297,"Percent of CC Pop":0.01,"Percent of Internet":0.0000,"Samples":41},
{"rank":156,"AS":199339,"Description":"INFRAGREEN","CC":"NO","Users":297,"Percent of CC Pop":0.01,"Percent of Internet":0.0000,"Samples":22},
{"rank":157,"AS":47753,"Description":"ONIT-AS","CC":"NO","Users":282,"Percent of CC Pop":0.01,"Percent of Internet":0.0000,"Samples":73},
{"rank":158,"AS":41949,"Description":"XTREME","CC":"NO","Users":271,"Percent of CC Pop":0.01,"Percent of Internet":0.0000,"Samples":13},
{"rank":159,"AS":201098,"Description":"NORDFJORDNETT","CC":"NO","Users":268,"Percent of CC Pop":0.01,"Percent of Internet":0.0000,"Samples":85},
{"rank":160,"AS":200139,"Description":"STATENS-VEGVESEN","CC":"NO","Users":267,"Percent of CC Pop":0.01,"Percent of Internet":0.0000,"Samples":167},
{"rank":161,"AS":44457,"Description":"LOVENSKIOLD-AS Oslo Norway","CC":"NO","Users":266,"Percent of CC Pop":0.01,"Percent of Internet":0.0000,"Samples":39},
{"rank":162,"AS":60068,"Description":"CDN77 _","CC":"NO","Users":253,"Percent of CC Pop":0.00,"Percent of Internet":0.0000,"Samples":130},
{"rank":163,"AS":200037,"Description":"NO-OSSELLE-AS","CC":"NO","Users":252,"Percent of CC Pop":0.00,"Percent of Internet":0.0000,"Samples":53},
{"rank":164,"AS":210615,"Description":"ALTA-KOMMUNE","CC":"NO","Users":249,"Percent of CC Pop":0.00,"Percent of Internet":0.0000,"Samples":141},
{"rank":165,"AS":41164,"Description":"GET-NO GET Norway","CC":"NO","Users":246,"Percent of CC Pop":0.00,"Percent of Internet":0.0000,"Samples":22},
{"rank":166,"AS":702,"Description":"UUNET - Verizon Business","CC":"NO","Users":244,"Percent of CC Pop":0.00,"Percent of Internet":0.0000,"Samples":22},
{"rank":167,"AS":207035,"Description":"NETS-USERS","CC":"NO","Users":240,"Percent of CC Pop":0.00,"Percent of Internet":0.0000,"Samples":11},
{"rank":168,"AS":34927,"Description":"IFOG-GMBH","CC":"NO","Users":239,"Percent of CC Pop":0.00,"Percent of Internet":0.0000,"Samples":11},
{"rank":169,"AS":214667,"Description":"IXT-GLOBAL IXT Global Network Operations","CC":"NO","Users":231,"Percent of CC Pop":0.00,"Percent of Internet":0.0000,"Samples":32},
{"rank":170,"AS":28852,"Description":"AERIS-AS","CC":"NO","Users":220,"Percent of CC Pop":0.00,"Percent of Internet":0.0000,"Samples":37},
{"rank":171,"AS":44764,"Description":"BITPRO","CC":"NO","Users":211,"Percent of CC Pop":0.00,"Percent of Internet":0.0000,"Samples":99},
{"rank":172,"AS":8473,"Description":"BAHNHOF","CC":"NO","Users":208,"Percent of CC Pop":0.00,"Percent of Internet":0.0000,"Samples":27},
{"rank":173,"AS":204027,"Description":"NO-BRREG","CC":"NO","Users":206,"Percent of CC Pop":0.00,"Percent of Internet":0.0000,"Samples":24},
{"rank":174,"AS":213158,"Description":"AS-NITTDAL","CC":"NO","Users":203,"Percent of CC Pop":0.00,"Percent of Internet":0.0000,"Samples":52},
{"rank":175,"AS":30967,"Description":"TRUPHONE-LTD","CC":"NO","Users":199,"Percent of CC Pop":0.00,"Percent of Internet":0.0000,"Samples":69},
{"rank":176,"AS":199900,"Description":"ASN-BEDSYS","CC":"NO","Users":198,"Percent of CC Pop":0.00,"Percent of Internet":0.0000,"Samples":17},
{"rank":177,"AS":44381,"Description":"ITSJEFEN-AS","CC":"NO","Users":191,"Percent of CC Pop":0.00,"Percent of Internet":0.0000,"Samples":85},
{"rank":178,"AS":36692,"Description":"CISCO-UMBRELLA - Cisco OpenDNS, LLC","CC":"NO","Users":190,"Percent of CC Pop":0.00,"Percent of Internet":0.0000,"Samples":154},
{"rank":179,"AS":55256,"Description":"NETSKOPE - Netskope Inc","CC":"NO","Users":190,"Percent of CC Pop":0.00,"Percent of Internet":0.0000,"Samples":33},
{"rank":180,"AS":198335,"Description":"TRANSATEL","CC":"NO","Users":187,"Percent of CC Pop":0.00,"Percent of Internet":0.0000,"Samples":28},
{"rank":181,"AS":34343,"Description":"BIP-AS BIP Backbone ASN","CC":"NO","Users":177,"Percent of CC Pop":0.00,"Percent of Internet":0.0000,"Samples":24},
{"rank":182,"AS":59978,"Description":"E-CO","CC":"NO","Users":173,"Percent of CC Pop":0.00,"Percent of Internet":0.0000,"Samples":17},
{"rank":183,"AS":212064,"Description":"TOLL-","CC":"NO","Users":169,"Percent of CC Pop":0.00,"Percent of Internet":0.0000,"Samples":17},
{"rank":184,"AS":203673,"Description":"AALESUND-ASN Aalesund Kommune ASN","CC":"NO","Users":167,"Percent of CC Pop":0.00,"Percent of Internet":0.0000,"Samples":28},
{"rank":185,"AS":54113,"Description":"FASTLY - Fastly, Inc.","CC":"NO","Users":166,"Percent of CC Pop":0.00,"Percent of Internet":0.0000,"Samples":121},
{"rank":186,"AS":204734,"Description":"HVALERBREDBAND","CC":"NO","Users":166,"Percent of CC Pop":0.00,"Percent of Internet":0.0000,"Samples":11},
{"rank":187,"AS":34100,"Description":"STORTINGET-AS","CC":"NO","Users":164,"Percent of CC Pop":0.00,"Percent of Internet":0.0000,"Samples":35},
{"rank":188,"AS":398830,"Description":"ICOMERA - Icomera US, Inc.","CC":"NO","Users":164,"Percent of CC Pop":0.00,"Percent of Internet":0.0000,"Samples":13},
{"rank":189,"AS":21171,"Description":"SCHIBSTED Schibsted ASA Autonomous system, Oslo, Norway","CC":"NO","Users":160,"Percent of CC Pop":0.00,"Percent of Internet":0.0000,"Samples":34},
{"rank":190,"AS":63473,"Description":"HOSTHATCH - HostHatch, LLC","CC":"NO","Users":160,"Percent of CC Pop":0.00,"Percent of Internet":0.0000,"Samples":19},
{"rank":191,"AS":203733,"Description":"ITPARTNER-","CC":"NO","Users":153,"Percent of CC Pop":0.00,"Percent of Internet":0.0000,"Samples":11},
{"rank":192,"AS":18701,"Description":"PPCO-US - ConocoPhillips Company","CC":"NO","Users":141,"Percent of CC Pop":0.00,"Percent of Internet":0.0000,"Samples":23},
{"rank":193,"AS":50229,"Description":"RIGNET-SOIL-AS","CC":"NO","Users":141,"Percent of CC Pop":0.00,"Percent of Internet":0.0000,"Samples":52},
{"rank":194,"AS":25225,"Description":"LOGNO-AS","CC":"NO","Users":136,"Percent of CC Pop":0.00,"Percent of Internet":0.0000,"Samples":53},
{"rank":195,"AS":60052,"Description":"ASN-FD","CC":"NO","Users":130,"Percent of CC Pop":0.00,"Percent of Internet":0.0000,"Samples":22},
{"rank":196,"AS":207189,"Description":"SANDEFJORD-LUFTHAVN","CC":"NO","Users":119,"Percent of CC Pop":0.00,"Percent of Internet":0.0000,"Samples":13},
{"rank":197,"AS":61213,"Description":"VISMA-AS","CC":"NO","Users":118,"Percent of CC Pop":0.00,"Percent of Internet":0.0000,"Samples":15},
{"rank":198,"AS":396982,"Description":"GOOGLE-CLOUD-PLATFORM - Google LLC","CC":"NO","Users":117,"Percent of CC Pop":0.00,"Percent of Internet":0.0000,"Samples":14},
{"rank":199,"AS":57858,"Description":"AS57858","CC":"NO","Users":113,"Percent of CC Pop":0.00,"Percent of Internet":0.0000,"Samples":25},
{"rank":200,"AS":202656,"Description":"XSERVERCLOUD","CC":"NO","Users":112,"Percent of CC Pop":0.00,"Percent of Internet":0.0000,"Samples":13},
{"rank":201,"AS":203061,"Description":"ITPROXIMUS","CC":"NO","Users":111,"Percent of CC Pop":0.00,"Percent of Internet":0.0000,"Samples":25},
{"rank":202,"AS":199791,"Description":"EMBRIQ-","CC":"NO","Users":110,"Percent of CC Pop":0.00,"Percent of Internet":0.0000,"Samples":11},
{"rank":203,"AS":204712,"Description":"DUETT","CC":"NO","Users":108,"Percent of CC Pop":0.00,"Percent of Internet":0.0000,"Samples":12},
{"rank":204,"AS":62186,"Description":"GJOVIK-KOMMUNE","CC":"NO","Users":91,"Percent of CC Pop":0.00,"Percent of Internet":0.0000,"Samples":10}
  ]
}
